{
  "creators": [],
  "difficulty": 3,
  "id": 76558750,
  "name": "Endless ❌",
  "percentToQualify": 53,
  "records": [
	{
	  "hz": 360,
	  "link": "https://youtu.be/0UWaycNzqdI",
	  "mobile": false,
	  "percent": 100,
	  "user": "Fusion425"
	},
	{
	  "hz": 60,
	  "link": "https://youtu.be/01N-BHZ4LOM",
	  "mobile": true,
	  "percent": 100,
	  "user": "Luk231"
	},
	{
	  "hz": 240,
	  "link": "https://www.youtube.com/watch?v=4dwvIlHs4zI",
	  "mobile": false,
	  "percent": 100,
	  "user": "culobdj"
	},
	{
	  "hz": 288,
	  "link": "https://youtu.be/ouaAEyegzio",
	  "mobile": false,
	  "percent": 100,
	  "user": "Armani"
	},
	{
	  "hz": 144,
	  "link": "https://youtu.be/vO14tymWU6M",
	  "mobile": false,
	  "percent": 100,
	  "user": "mrperson"
	},
	{
	  "hz": 288,
	  "link": "https://youtu.be/CCJO0A8SoVc",
	  "mobile": false,
	  "percent": 100,
	  "user": "Blathers"
	},
	{
	  "hz": 240,
	  "link": "https://www.youtube.com/watch?v=w6MwY-AusXw",
	  "mobile": false,
	  "percent": 100,
	  "user": "Lev_Nix"
	},
	{
	  "hz": 360,
	  "link": "https://www.youtube.com/watch?v=C5naWhje4n4",
	  "mobile": false,
	  "percent": 100,
	  "user": "rustic"
	},
	{
	  "hz": 120,
	  "link": "https://www.youtube.com/watch?v=eOQSbK_vi_k",
	  "mobile": false,
	  "percent": 100,
	  "user": "ZeusGD"
	},
	{
	  "hz": 360,
	  "link": "https://www.youtube.com/watch?v=YVr88h5WA5I",
	  "mobile": false,
	  "percent": 100,
	  "user": "zDark"
	},
	{
	  "hz": 360,
	  "link": "https://youtu.be/QevVjQHJm2Q",
	  "mobile": false,
	  "percent": 100,
	  "user": "Mystikl"
	},
	{
	  "hz": 120,
	  "link": "https://youtu.be/SYrYItbuiI0",
	  "mobile": true,
	  "percent": 100,
	  "user": "sikoo23"
	},
	{
	  "hz": 240,
	  "link": "https://www.youtube.com/watch?v=fjxk4OOLIWM&ab_channel=DELETE999%5BGD%5D",
	  "mobile": false,
	  "percent": 100,
	  "user": "DeleteNine"
	},
	{
	  "hz": 60,
	  "link": "https://www.youtube.com/watch?v=5doHHAngZmw",
	  "mobile": false,
	  "percent": 100,
	  "user": "Super26Ramo"
	},
	{
	  "hz": 360,
	  "link": "https://youtu.be/Zu2cfV6HFcU",
	  "mobile": false,
	  "percent": 100,
	  "user": "Acacia"
	},
	{
	  "hz": 360,
	  "link": "https://www.youtube.com/watch?v=X9MeQHYm8ns",
	  "mobile": false,
	  "percent": 100,
	  "user": "Skybolt06"
	},
	{
	  "enjoyment": "8",
	  "hz": 60,
	  "link": "https://youtu.be/1OJPuuDVUv8",
	  "mobile": true,
	  "percent": 100,
	  "user": "Poke Zach"
	},
	{
	  "hz": 60,
	  "link": "https://youtu.be/aGuy3GRF9eA",
	  "mobile": true,
	  "percent": 100,
	  "user": "agentgiscool"
	},
	{
	  "enjoyment": "9",
	  "hz": 60,
	  "link": "https://www.youtube.com/watch?v=cpAXwIkG_4M",
	  "mobile": false,
	  "percent": 100,
	  "user": "Xeronius"
	},
	{
	  "enjoyment": 8,
	  "hz": 240,
	  "link": "https://www.youtube.com/watch?v=PBbEYkFg_xY",
	  "mobile": false,
	  "percent": 100,
	  "user": "rastuyas"
	},
	{
	  "enjoyment": 8,
	  "hz": 360,
	  "link": "https://youtu.be/RS5xYEMCZR0?si=J9Ul46WZFRJoWne5",
	  "mobile": false,
	  "percent": 100,
	  "user": "Hyperbeat"
	},
	{
	  "enjoyment": 7,
	  "hz": 60,
	  "link": "https://youtu.be/Cc7-fIAXaAE",
	  "mobile": true,
	  "percent": 100,
	  "user": "Blysteryx"
	}
  ],
  "song": "Creo - Endless",
  "verification": "https://youtu.be/EoUWB_gkkhk",
  "verifier": "Sal752"
}