{
    "id": 100199070,
    "name": "Femboi Anthem",
    "author": "The16FigureLimit",
    "creators": [],
    "verifier": "The16FigureLimit",
    "verification": "https://youtu.be/QqL4wLJMhUQ",
    "percentToQualify": 48,
    "song": "YOASOBI - Racing Into The Night",
    "songLink": "https://cdn.discordapp.com/attachments/876044908836847617/1214007017103032370/1024087.mp3?ex=65f78b24&is=65e51624&hm=4f6bcdeb2180f3eb625e7ea6459ad7a46bc96abf49445e53aadd3b20e63c1b9a&",
    "difficulty": 7,
    "records": [
        
    ]
}
