{
    "id": 97646830,
    "name": "Flow",
    "author": "Solelak",
    "creators": [],
    "verifier": "Hyperbeat",
    "verification": "https://youtu.be/dDd4i5iG-K8",
    "percentToQualify": 100,
    "song": "Creo - Flow",
    "difficulty": 0,
    "records": [
        {
            "user": "Solelak",
            "link": "https://www.youtube.com/watch?v=E13FBkkz8k8",
            "percent": 100,
            "hz": 60,
            "mobile": false
        },
        {
            "user": "Xeronius",
            "link": "https://youtu.be/pYAfhPeUQIw",
            "percent": 100,
            "hz": 75,
            "mobile": false
        },
        {
            "user": "Thomas Jefferson",
            "link": "https://youtu.be/pTYtVzVkQOU",
            "percent": 100,
            "hz": 240,
            "mobile": false
        },
        {
            "user": "rfanvs",
            "link": "https://youtu.be/UwugQC6f2DU",
            "percent": 100,
            "hz": 240,
            "mobile": false
        },
         {
            "user": "sn0w",
            "link": "https://youtu.be/NaXvRJMMrVU",
            "percent": 100,
            "hz": 240,
            "mobile": false
        },
        {
            "user": "Blysteryx",
            "link": "https://youtu.be/CuW0kkBqMho?si=OifhHf6RU86AoNR3",
            "percent": 100,
            "hz": 120,
            "mobile": false
        },
        {
            "user": "Poke Zach",
            "link": "https://youtu.be/ZcI6WNDHOD8?si=XmFS9LScIaFnOSBA",
            "percent": 100,
            "hz": 60,
            "mobile": true
        },
        {
            "user": "whitmp4",
            "link": "https://youtu.be/Tgp-0hPCq5E?si=7x2qjipGFMzu4T9z",
            "percent": 100,
            "hz": 240,
            "mobile": false
        },
        {
            "user": "syrcx",
            "link": "https://youtu.be/ExO9z0SIc98",
            "percent": 100,
            "hz": 240,
            "mobile": false
        },
        {
            "user": "LimeDub",
            "link": "https://youtu.be/rt35R9QU0Xk",
            "percent": 100,
            "hz": 288,
            "mobile": false
        },
        {
            "user": "DELETE999",
            "link": "https://youtu.be/eCrJ136rEVI?si=QwYokT5q661xdq4a",
            "percent": 100,
            "hz": 360,
            "mobile": false
        },
        {
            "user": "Popples",
            "link": "https://youtu.be/ljQtw9EUObg?si=R3x816lAc32QuGY8",
            "percent": 100,
            "hz": 120,
            "mobile": false
        },
        {
            "user": "Alvaneder",
            "link": "https://www.youtube.com/watch?v=hjLGrMKZkVI",
            "percent": 100,
            "hz": 144,
            "mobile": false
        },
        {
            "user": "ArctiixPaladin",
            "link": "https://www.youtube.com/watch?v=Zi-n3OwVGTQ",
            "percent": 100,
            "hz": 120,
            "mobile": false
        }
    ]
}
