{
	"id": 123460764,
	"name": "Forget You",
	"creators": [
		"Salukis"
	],
	"verifier": "Salukis",
	"verification": "https://youtu.be/YAf9D5KL0_4",
	"percentToQualify": 100,
	"password": "Free to copy",
	"difficulty": 1,
	"song": "Ceelo Green- Forget You",
	"songLink": "https://cdn.discordapp.com/ephemeral-attachments/1320592923561164871/1397716774438440992/1083646.mp3?ex=68840e2f&is=6882bcaf&hm=dc722e003b43f31de5b5110e05ef27a9ec9ab5e9e866323b39ea79846a9f53dc&",
	"records": [
		{
			"user": "Solo12",
			"link": "https://youtu.be/cz3SgYFUHwI",
			"percent": 100,
			"hz": 360,
			"enjoyment": 9
		},
		{
			"user": "Screendoe",
			"link": "https://medal.tv/games/geometry-dash/clips/kKHMr1bbR7AZUMy5V?invite=cr-MSxaWU4sMjEyMTU0NjM2&v=124",
			"percent": 100,
			"hz": 240,
			"enjoyment": 10
		}
	]
}