{
    "id": 106763860,
    "name": "How by Spu7nix",
    "author": "Jackyy",
    "creators": ["Rico"],
    "verifier": "Deltaflare",
    "verification": "https://youtu.be/-UQdIWhvD5Y?si=UuVF-aVgUwU0DFiZ",
    "percentToQualify": 100,
    "song": "Exyl x Paper Skies - How",
    "difficulty": 2,
    "records": [
        {
            "user": "Hyperbeat",
            "link": "https://youtu.be/ejyfIH8Hh-w?feature=shared",
            "percent": 100,
            "hz": 240,
            "mobile": false,
            "enjoyment": 8
        },
        {
            "user": "Mystikl",
            "link": "https://youtu.be/ciKpZL-jxTk",
            "percent": 100,
            "hz": 360,
            "mobile": false,
            "enjoyment": 7
        }
    ]
}
