{
    "id": 62803674,
    "name": "not so strange",
    "author": "lespainsaucho",
    "creators": [],
    "verifier": "lespainsaucho",
    "verification": "https://youtu.be/D3rcEEOQUKc",
    "percentToQualify": 100,
    "song": "Schtiffles - Beep Beep",
    "difficulty": 0,
    "records": [
        {
            "user": "ZBosGaming",
            "link": "https://www.youtube.com/watch?v=GOYR34nW8sY",
            "percent": 100,
            "hz": 360,
            "mobile": false
        },
        {
            "user": "Kind1e",
            "link": "https://youtu.be/NCKdOp3sTxY",
            "percent": 100,
            "hz": 165,
            "mobile": false
        },
        {
            "user": "sqrtpie",
            "link": "https://www.youtube.com/watch?v=PLi9ULaKQA4&t=557",
            "percent": 100,
            "hz": 60,
            "mobile": false
        },
        {
            "user": "EmeraldOre",
            "link": "https://www.youtube.com/watch?v=lrOl3IcIL8g",
            "percent": 100,
            "hz": 120,
            "mobile": false
        },
        {
            "user": "matt843",
            "link": "https://youtu.be/Lgb1zl-Blm4",
            "percent": 100,
            "hz": 85,
            "mobile": false
        },
        {
            "user": "Ventism",
            "link": "https://www.youtube.com/watch?v=QDCUpqhU1Lk",
            "percent": 100,
            "hz": 144,
            "mobile": false
        },
        {
            "user": "ThunderStorm36",
            "link": "https://www.youtube.com/watch?v=Onai8COqqSo",
            "percent": 100,
            "hz": 60,
            "mobile": false
        },
        {
            "user": "Agentgiscool",
            "link": "https://youtu.be/L8l69EZ7_ro",
            "percent": 100,
            "hz": 60,
            "mobile": true
        },
        {
            "user": "ThisGuyKreas",
            "link": "https://m.youtube.com/watch?v=05d3ZCwG46Y&t=2s",
            "percent": 100,
            "hz": 60,
            "mobile": true
        },
        {
            "user": "AuditLog",
            "link": "https://youtu.be/DQMwIeOsQ8Q",
            "percent": 100,
            "hz": 60,
            "mobile": true
        },
        {
            "user": "mrperson",
            "link": "https://www.youtube.com/watch?v=udQBa6Pzq0M",
            "percent": 100,
            "hz": 144,
            "mobile": false
        },
        {
            "user": "ToastyBois",
            "link": "https://youtu.be/65Q1tF26PUQ",
            "percent": 100,
            "hz": 144,
            "mobile": false
        },
        {
            "user": "Fusion425",
            "link": "https://youtu.be/y_Dciuy2Jhs",
            "percent": 100,
            "hz": 360,
            "mobile": false
        },
        {
            "user": "TheUltraBlock",
            "link": "https://www.youtube.com/watch?v=IElhBu2wSe0",
            "percent": 100,
            "hz": 60,
            "mobile": false
        },
        {
            "user": "culobdj",
            "link": "https://www.youtube.com/watch?v=BuLuYNEtelo",
            "percent": 100,
            "hz": 240,
            "mobile": false
        },
        {
            "user": "danielvess555",
            "link": "https://www.youtube.com/watch?v=9VThW-uzPjU",
            "percent": 100,
            "hz": 240,
            "mobile": false
        },
        {
            "user": "MilkshakeGD",
            "link": "https://www.youtube.com/watch?v=iRb9zLcxdAo",
            "percent": 100,
            "hz": 165,
            "mobile": false
        },
        {
            "user": "Moisty",
            "link": "https://youtu.be/A-iY3_7A61g",
            "percent": 100,
            "hz": 60,
            "mobile": false
        },
        {
            "user": "Mystikl",
            "link": "https://youtu.be/KMM3s9iraps",
            "percent": 100,
            "hz": 60,
            "mobile": true
        },
        {
            "user": "Armani",
            "link": "https://youtu.be/5DPRsUFdEMo",
            "percent": 100,
            "hz": 240,
            "mobile": false
        },
        {
            "user": "Xilver171",
            "link": "https://youtu.be/wIue75cPL3M",
            "percent": 100,
            "hz": 60,
            "mobile": true
        },
        {
            "user": "Solo12",
            "link": "https://www.youtube.com/watch?v=K-bGtXlLWhU",
            "percent": 100,
            "hz": 60,
            "mobile": true
        },
        {
            "user": "Gusters",
            "link": "https://www.youtube.com/watch?v=7h9CqFfynD0",
            "percent": 100,
            "hz": 60,
            "mobile": false
        },
        {
            "user": "Ralta",
            "link": "https://www.youtube.com/watch?v=qq5oQ7ci8gY",
            "percent": 100,
            "hz": 60,
            "mobile": true
        },
        {
            "user": "DJJDK",
            "link": "https://youtu.be/J-Td7nKZsS4",
            "percent": 100,
            "hz": 240,
            "mobile": false
        },
        {
            "user": "ReNL",
            "link": "https://www.youtube.com/watch?v=Az4zlsEyJTM",
            "percent": 100,
            "hz": 60,
            "mobile": false
        },
        {
            "user": "Xyan",
            "link": "https://www.youtube.com/watch?v=Az4zlsEyJTM",
            "percent": 100,
            "hz": 60,
            "mobile": false
        },
        {
            "user": "H3lpFul",
            "link": "https://youtu.be/4yBN30va8KY",
            "percent": 100,
            "hz": 360,
            "mobile": false
        },
        {
            "user": "Nooob07",
            "link": "https://www.youtube.com/watch?v=4oFgxQgpQpI",
            "percent": 100,
            "hz": 60,
            "mobile": false
        },
        {
            "user": "zDarkHTR",
            "link": "https://youtu.be/oVwn4wujLpA",
            "percent": 100,
            "hz": 360,
            "mobile": false
        },
        {
            "user": "DELETE999",
            "link": "https://youtu.be/UtDKI7LI4Eo",
            "percent": 100,
            "hz": 240,
            "mobile": false
        },
        {
            "user": "ArctiixPaladin",
            "link": "https://youtu.be/mFFx65nYasQ",
            "percent": 100,
            "hz": 240,
            "mobile": false
        },
        {
            "user": "SinSnrGD",
            "link": "https://youtu.be/eRYc3rPPmDU",
            "percent": 100,
            "hz": 60,
            "mobile": true
        }
    ]
}
