{
  "creators": [
	"hjog"
  ],
  "difficulty": 9,
  "enjoyment": 6,
  "id": 110101194,
  "name": "PROJECT E",
  "percentToQualify": 60,
  "records": [
	{
	  "enjoyment": 8,
	  "hz": 360,
	  "link": "https://youtu.be/bxoJKoCuN9Y",
	  "mobile": false,
	  "percent": 100,
	  "user": "Mystikl"
	},
	{
	  "enjoyment": 9,
	  "hz": 240,
	  "link": "https://www.youtube.com/watch?v=0N3vP5d2yAk",
	  "mobile": false,
	  "percent": 100,
	  "user": "attrixia"
	},
	{
	  "enjoyment": 8,
	  "hz": 240,
	  "link": "https://youtu.be/_6vz2ACnM0M?si=jTvBkJOKVtuXzhsY",
	  "mobile": false,
	  "percent": 100,
	  "user": "Hydraniac"
	},
	{
	  "enjoyment": 8,
	  "hz": 240,
	  "link": "https://youtu.be/lJ2N9o6s5oo?si=q_ILaUgfOEqHGWDY",
	  "mobile": false,
	  "percent": 100,
	  "user": "Syrcx"
	}
  ],
  "song": "Waterflame - Control: Mind",
  "verification": "https://youtu.be/8ZWurIInmo4",
  "verifier": "Riley"
}