{
  "creators": [
	"Blysteryx"
  ],
  "difficulty": 2,
  "id": 97125608,
  "name": "Swirling Skyscape",
  "percentToQualify": 100,
  "records": [
	{
	  "hz": 360,
	  "link": "https://youtu.be/y45SONuYuGM",
	  "mobile": false,
	  "percent": 100,
	  "user": "Mystikl"
	},
	{
	  "enjoyment": "9",
	  "hz": 75,
	  "link": "https://youtu.be/WfNv6LLcxk4",
	  "mobile": false,
	  "percent": 100,
	  "user": "Xeronius"
	},
	{
	  "hz": 360,
	  "link": "https://youtu.be/TJh-lAbAdCM?si=SKtyMKFGtbxQiZTZ",
	  "mobile": false,
	  "percent": 100,
	  "user": "DeleteNine"
	},
	{
	  "hz": 360,
	  "link": "https://www.youtube.com/watch?v=eRv4TEWoHlc",
	  "mobile": false,
	  "percent": 100,
	  "user": "zDark"
	},
	{
	  "enjoyment": "6",
	  "hz": 60,
	  "link": "https://youtu.be/RK2FfPR7juU?si=KEXCBK7CqrN_r8hF",
	  "mobile": true,
	  "percent": 100,
	  "user": "Poke Zach"
	},
	{
	  "enjoyment": 4,
	  "hz": 240,
	  "link": "https://youtu.be/hykRQQRBkLU",
	  "mobile": false,
	  "percent": 100,
	  "user": "evil"
	},
	{
	  "enjoyment": 6,
	  "hz": 240,
	  "link": "https://youtu.be/1hP4hDkjvk0",
	  "mobile": false,
	  "percent": 100,
	  "user": "rastuyas"
	},
	{
	  "hz": 144,
	  "link": "https://www.youtube.com/watch?v=Da7iFmdsKrA&feature=youtu.be",
	  "mobile": false,
	  "percent": 100,
	  "user": "Alvaneder"
	},
	{
	  "enjoyment": 9,
	  "hz": 360,
	  "link": "https://youtu.be/znfHHXTPk8k?si=00-khqDAyvSAVnQH",
	  "mobile": false,
	  "percent": 100,
	  "user": "Hyperbeat"
	}
  ],
  "song": "wispx - Idyllic",
  "verification": "https://youtu.be/yG_SwZRZMPw?si=Q1qKb08tqW1gUywL",
  "verifier": "Blysteryx"
}