{
    "id": 86863834,
    "name": "ULTIMATE",
    "author": "Huskiegaming",
    "creators": [],
    "verifier": "Huskiegaming",
    "verification": "https://youtu.be/oykvwEiZbok",
    "percentToQualify": 100,
    "song": "Skorde x Nateki - ULTIMATE",
    "difficulty": 3,
    "records": [
        {
            "user": "Poke Zach",
            "link": "https://youtu.be/24ZQFe8uPPI",
            "percent": 100,
            "hz": 60,
            "mobile": true
        },
        {
            "user": "Mystikl",
            "link": "https://youtu.be/XRy0gVjGn7Q",
            "percent": 100,
            "hz": 360,
            "mobile": false
        },
        {
            "user": "hab",
            "link": "https://youtu.be/UHOsS3QBJrU",
            "percent": 100,
            "hz": 300,
            "mobile": false
        },
        {
            "user": "hayden",
            "link": "https://youtu.be/qrET40iO-qY",
            "percent": 100,
            "hz": 360,
            "mobile": false
        },
        {
            "user": "mrperson",
            "link": "https://youtu.be/lHdEDpDLTyU",
            "percent": 100,
            "hz": 144,
            "mobile": false
        },
        {
            "user": "Hyperbeat",
            "link": "https://www.youtube.com/watch?v=RS5xYEMCZR0",
            "percent": 100,
            "hz": 360,
            "mobile": false
        },
        {
            "user": "whitmp4",
            "link": "https://youtu.be/eW6w4j6vYTc?si=MicAnJ4Qubh9Irti",
            "percent": 100,
            "hz": 360,
            "mobile": false
        },
        {
            "user": "Tupi",
            "link": "https://www.youtube.com/watch?v=E4YpXEWBhCc",
            "percent": 100,
            "hz": 120,
            "mobile": false
        },
         {
            "user": "Blueberry",
            "link": "https://youtu.be/y5bl9zKj4zI",
            "percent": 100,
            "hz": 360,
            "mobile": false
        },
          {
            "user": "Tanginess",
            "link": "https://medal.tv/games/geometry-dash/clips/1CLJzhb8KVLvzV/d1337ikRpTP3?invite=cr-MSxXeGosMTcyNjQxMzAxLA",
            "percent": 100,
            "hz": 165,
            "mobile": false
        },
        {
          "user": "Iza",
          "link": "https://www.youtube.com/watch?v=uc1LjM7-Q7g&ab_channel=Sakira",
          "percent": 100,
          "hz": 144,
          "mobile": false
        },
        {
          "user": "Xeronius",
          "link": "https://youtu.be/ZdupHD76TMw?si=Y5W9ChlTx72cuwAz",
          "percent": 100,
          "hz": 75,
          "mobile": false
        },
        {
            "user": "briskrain",
            "link": "https://youtu.be/FQpO4oF5Lr4?si=ozc9p0Mz6WLxqodJ",
            "percent": 100,
            "hz": 144,
            "mobile": false
        },
        {
            "user": "DeleteNine",
            "link": "https://www.youtube.com/watch?v=AMELW2kXTmg",
            "percent": 100,
            "hz": 360,
            "mobile": false
        }
    ]
}
