{
    "id": 80914165,
    "name": "Unordinary Life",
    "author": "Xeronius",
    "creators": [],
    "verifier": "Xeronius",
    "verification": "https://www.youtube.com/watch?v=BiN1Ma_nkUs",
    "percentToQualify": 100,
    "song": "The Living Tombstone - My Ordinary Life",
    "difficulty": 3,
    "records": [
         {
            "user": "Zyxo",
            "link": "https://youtu.be/ooXpj0D1pPQ?si=k6MjRLBpX72ovGzA",
            "percent": 100,
            "hz": 60,
            "mobile": true
        },
          {
            "user": "whitmp4",
            "link": "https://youtu.be/UJtvyJ-9L0c?si=OTXreI8GXrGGf8qC",
            "percent": 100,
            "hz": 360,
            "mobile": false
        },
         {
            "user": "mrperson",
            "link": "https://youtu.be/AEK_TS_0PfI",
            "percent": 100,
            "hz": 144,
            "mobile": false
        },
        {
            "user": "hayden",
            "link": "https://youtu.be/UPSk2fp723Y",
            "percent": 100,
            "hz": 360,
            "mobile": false
        },
        {
            "user": "Hyperbeat",
            "link": "https://www.youtube.com/watch?v=BU5Ms7PJ6D4",
            "percent": 100,
            "hz": 360,
            "mobile": false
        },
        {
            "user": "Mystikl",
            "link": "https://youtu.be/yiR2n_7Zc98",
            "percent": 100,
            "hz": 360,
            "mobile": false
        }
    ]
}
